styler_validation/__init__.py
styler_validation/messages.py
styler_validation/validators.py
styler_validation-1.0.0.dist-info/LICENSE
styler_validation-1.0.0.dist-info/METADATA
styler_validation-1.0.0.dist-info/WHEEL
styler_validation-1.0.0.dist-info/top_level.txt
styler_validation-1.0.0.dist-info/RECORD
