Metadata-Version: 2.1
Name: styler-validation
Version: 1.0.0
Summary: Validators to be used as mixins in models
Home-page: https://github.com/STYLER-Inc/styler-validation
Author: Bruno Toshio Sugano
Author-email: brunotoshio@gmail.com
License: MIT license
Keywords: styler_validation
Platform: UNKNOWN
Classifier: Intended Audience :: Developers
Classifier: License :: OSI Approved :: MIT License
Classifier: Natural Language :: English
Classifier: Programming Language :: Python :: 3
Classifier: Programming Language :: Python :: 3.6
Classifier: Programming Language :: Python :: 3.7
Classifier: Programming Language :: Python :: 3.8
Requires-Python: >=3.6
